Metadata-Version: 2.1
Name: secretserverpy
Version: 0.0.1
Summary: Package to interact and automate against Secret Server REST API
Home-page: https://github.com/realpython/reader
Author: Shawn Melton
Author-email: shawn.melton@thycotic.com
License: UNKNOWN
Platform: UNKNOWN
Classifier: Development Status :: 1 - Planning
Classifier: Intended Audience :: Developers
Classifier: Topic :: Software Development :: Build Tools
Classifier: Programming Language :: Python :: 3.7
Classifier: Programming Language :: Python :: 3.8
Classifier: Programming Language :: Python :: 3.9
Classifier: License :: OSI Approved :: Apache Software License
Classifier: Operating System :: OS Independent
Classifier: Natural Language :: English
Classifier: Topic :: Security
Classifier: Topic :: Software Development
Classifier: Topic :: Software Development :: Libraries
Classifier: Topic :: Software Development :: Libraries :: Python Modules
Classifier: Topic :: Utilities
License-File: LICENSE
